{
  "project_info": {
    "project_number": "999423835574",
    "firebase_url": "https://musicplayerapp-aed33-default-rtdb.asia-southeast1.firebasedatabase.app",
    "project_id": "musicplayerapp-aed33",
    "storage_bucket": "musicplayerapp-aed33.firebasestorage.app"
  },
  "client": [
    {
      "client_info": {
        "mobilesdk_app_id": "1:999423835574:android:ae7b2bd27de6c2c4395517",
        "android_client_info": {
          "package_name": "com.example.myapplication"
        }
      },
      "oauth_client": [
        {
          "client_id": "999423835574-31f0ilc65i7m48iqcf753mvkun84k05h.apps.googleusercontent.com",
          "client_type": 1,
          "android_info": {
            "package_name": "com.example.myapplication",
            "certificate_hash": "00662cd913ca1f76ecd9ea940cb80d39a69cd46b"
          }
        },
        {
          "client_id": "999423835574-d61eih7sqaiu0oj6fvclftkjvf6e49ms.apps.googleusercontent.com",
          "client_type": 1,
          "android_info": {
            "package_name": "com.example.myapplication",
            "certificate_hash": "4f1061d0c466a1f0170bb9012fcf796da6102626"
          }
        },
        {
          "client_id": "999423835574-tkviltngm6nh400oau7vsogit2v8ns0t.apps.googleusercontent.com",
          "client_type": 1,
          "android_info": {
            "package_name": "com.example.myapplication",
            "certificate_hash": "5614a243954e54e3210a06e7f53f5ce077b2f1d0"
          }
        },
        {
          "client_id": "999423835574-ulab4v43mio7e39e1td0obbhda0ui1bv.apps.googleusercontent.com",
          "client_type": 3
        }
      ],
      "api_key": [
        {
          "current_key": "AIzaSyBTHJHiDSOxb4NauWGIzs_YYaFUtpHjrkQ"
        }
      ],
      "services": {
        "appinvite_service": {
          "other_platform_oauth_client": [
            {
              "client_id": "999423835574-ulab4v43mio7e39e1td0obbhda0ui1bv.apps.googleusercontent.com",
              "client_type": 3
            }
          ]
        }
      }
    }
  ],
  "configuration_version": "1"
}